autoplot
