Metadata-Version: 1.0
Name: autoplot
Version: 0.8.1
Summary: Interface to Autoplot Java library
Home-page: https://github.com/autoplot/python/
Author: Jeremy Faden
Author-email: faden@cottagesystems.com
License: LICENSE.txt
Platform: UNKNOWN
